MANIFEST.in
README.rst
setup.py
logjam/__init__.py
logjam/base_uploader.py
logjam/compress.py
logjam/parse.py
logjam/s3_uploader.py
logjam/service.py
logjam/upload.py
logjam.egg-info/PKG-INFO
logjam.egg-info/SOURCES.txt
logjam.egg-info/dependency_links.txt
logjam.egg-info/requires.txt
logjam.egg-info/top_level.txt
scripts/logjam-compress
scripts/logjam-upload