Metadata-Version: 1.0
Name: logjam
Version: 0.0.3
Summary: Small tools for archiving ISO8601 logfiles
Home-page: https://github.com/hblanks/logjam
Author: Hunter Blanks
Author-email: hblanks@artifex.org
License: MIT License
Platform: UNKNOWN
